dynamoquick/__init__.py
dynamoquick/core.py
dynamoquick/helper.py
dynamoquick-1.0.0.dist-info/METADATA
dynamoquick-1.0.0.dist-info/WHEEL
dynamoquick-1.0.0.dist-info/top_level.txt
dynamoquick-1.0.0.dist-info/RECORD
