Metadata-Version: 2.1
Name: dynamoquick
Version: 1.0.0
Summary: A small example package
Author: Zuhair
Author-email: author@example.com
License: UNKNOWN
Keywords: python,dynamodb,tables
Platform: UNKNOWN
Classifier: Development Status :: 1 - Planning
Classifier: Intended Audience :: Developers
Classifier: Programming Language :: Python :: 3
Classifier: Operating System :: OS Independent
Requires-Python: >=3.7
Requires-Dist: boto3 (>=1.21.10)
Requires-Dist: botocore (>=1.24.10)
